familiar_gemini/__init__.py
familiar_gemini-0.1.1.dist-info/licenses/LICENSE
familiar_gemini-0.1.1.dist-info/METADATA
familiar_gemini-0.1.1.dist-info/WHEEL
familiar_gemini-0.1.1.dist-info/entry_points.txt
familiar_gemini-0.1.1.dist-info/top_level.txt
familiar_gemini-0.1.1.dist-info/RECORD
