Metadata-Version: 2.4
Name: familiar-gemini
Version: 0.1.1
Summary: gemini cli agent plugin for familiar
Author-email: cyberwitchery lab <contact@cyberwitchery.com>
License-Expression: MIT
Project-URL: Homepage, https://github.com/cyberwitchery/familiar-gemini
Project-URL: Repository, https://github.com/cyberwitchery/familiar-gemini
Keywords: ai,agents,gemini,familiar
Requires-Python: >=3.10
License-File: LICENSE
Requires-Dist: familiar-cli>=0.3.1
Provides-Extra: dev
Requires-Dist: ruff; extra == "dev"
Requires-Dist: mypy; extra == "dev"
Requires-Dist: pytest; extra == "dev"
Dynamic: license-file
